wrap/__init__.py
wrap/exception.py
wrap/flow.py
wrap/show.py
wrap-2018.2.2.dist-info/DESCRIPTION.rst
wrap-2018.2.2.dist-info/METADATA
wrap-2018.2.2.dist-info/RECORD
wrap-2018.2.2.dist-info/WHEEL
wrap-2018.2.2.dist-info/metadata.json
wrap-2018.2.2.dist-info/top_level.txt
