Metadata-Version: 2.0
Name: wrap
Version: 2018.2.2
Summary: useful wrap collections
Home-page: https://github.com/pingf/wrap.git
Author: Jesse MENG
Author-email: pingf0@gmail.com
License: MIT
Platform: any
Classifier: Intended Audience :: Developers
Classifier: License :: OSI Approved :: BSD License
Classifier: Operating System :: OS Independent
Classifier: Programming Language :: Python
Classifier: Topic :: Software Development :: Libraries :: Python Modules
Requires-Dist: logcc
